PWE_NB_Extension/__init__.py
PWE_NB_Extension/helper.py
PWE_NB_Extension/Prolog-Codemirror-Mode/prolog/README.md
PWE_NB_Extension/Prolog-Codemirror-Mode/prolog/index.html
PWE_NB_Extension/Prolog-Codemirror-Mode/prolog/prolog-ctype.js
PWE_NB_Extension/Prolog-Codemirror-Mode/prolog/prolog-enhanced.png
PWE_NB_Extension/Prolog-Codemirror-Mode/prolog/prolog-template-hint.css
PWE_NB_Extension/Prolog-Codemirror-Mode/prolog/prolog-template-hint.js
PWE_NB_Extension/Prolog-Codemirror-Mode/prolog/prolog.js
PWE_NB_Extension/Prolog-Codemirror-Mode/prolog/prolog_keys.js
PWE_NB_Extension/Prolog-Codemirror-Mode/prolog/prolog_op.js
PWE_NB_Extension/Prolog-Codemirror-Mode/prolog/prolog_query.js
PWE_NB_Extension/Prolog-Codemirror-Mode/prolog/prolog_server.js
PWE_NB_Extension-0.0.6.dist-info/LICENSE
PWE_NB_Extension-0.0.6.dist-info/METADATA
PWE_NB_Extension-0.0.6.dist-info/WHEEL
PWE_NB_Extension-0.0.6.dist-info/top_level.txt
PWE_NB_Extension-0.0.6.dist-info/RECORD
