Metadata-Version: 2.1
Name: PWE-NB-Extension
Version: 0.0.6
Summary: A Notebook Extension for the Possible Worlds Explorer
Home-page: https://github.com/idaks/PWE-NB-Extension
Author: Sahil Gupta
Author-email: 
License: UNKNOWN
Platform: UNKNOWN
Classifier: Programming Language :: Python :: 3
Classifier: License :: OSI Approved :: MIT License
Classifier: Operating System :: OS Independent
Requires-Dist: PW-explorer (>=0.0.23)
Requires-Dist: IPython (>=7.3.0)
Requires-Dist: notebook (>=5.7.0)
Requires-Dist: Pygments (>=2.2.0)
